example/__init__.py
example/dataset_generation_parallel.py
example/fix_old_calidation_star_catalogue.py
mccd/__init__.py
mccd/auxiliary_fun.py
mccd/dataset_generation.py
mccd/grads.py
mccd/info.py
mccd/mccd.py
mccd/mccd_utils.py
mccd/proxs.py
mccd/utils.py
tests/__init__.py
tests/test_pysap_wavelet.py
tests/hidden_tests/__init__.py
tests/hidden_tests/test_config_fit_MCCD.py
tests/hidden_tests/test_fit_simil_notebook.py
tests/hidden_tests/test_preprocessing.py
tests/hidden_tests/test_recover_PSFs.py
mccd-1.2.4.dist-info/LICENCE.txt
mccd-1.2.4.dist-info/METADATA
mccd-1.2.4.dist-info/WHEEL
mccd-1.2.4.dist-info/top_level.txt
mccd-1.2.4.dist-info/RECORD
