Metadata-Version: 2.1
Name: mccd
Version: 1.2.4
Summary: builtins
Home-page: https://github.com/CosmoStat/mccd
Author: Tobias Liaudat
Author-email: tobiasliaudat@gmail.com
License: MIT
Classifier: Programming Language :: Python :: 3.6
Classifier: License :: OSI Approved :: MIT License
Classifier: Operating System :: MacOS
Classifier: Operating System :: POSIX :: Linux
Classifier: Topic :: Scientific/Engineering
Classifier: Intended Audience :: Science/Research
Classifier: Intended Audience :: Developers
License-File: LICENCE.txt
Requires-Dist: numpy (>=1.19.5)
Requires-Dist: scipy (>=1.5.4)
Requires-Dist: modopt (>=1.5.1)
Requires-Dist: astropy (>=4.0.2)
Requires-Dist: python-pysap (>=0.0.6)
